__init__.py
tempus/__init__.py
tempus/agents/__init__.py
tempus/agents/quant_agent.py
tempus/data/__init__.py
tempus/data/dex_client.py
tempus/data/pump_fun_client.py
tempus/prompt_templates/__init__.py
tempus/prompt_templates/quant_ai.py
tempus/tools/__init__.py
tempus/tools/market_analysis.py
tempus_labs-1.0.2.dist-info/LICENSE
tempus_labs-1.0.2.dist-info/METADATA
tempus_labs-1.0.2.dist-info/WHEEL
tempus_labs-1.0.2.dist-info/top_level.txt
tempus_labs-1.0.2.dist-info/RECORD
