Metadata-Version: 2.2
Name: tempus-labs
Version: 1.0.2
Summary: Next-Gen Quant AI Agents Framework on Solana
Requires-Python: >=3.10
License-File: LICENSE
Requires-Dist: beautifulsoup4>=4.12.3
Requires-Dist: langchain>=0.3.15
Requires-Dist: langchain-community>=0.3.15
Requires-Dist: langchain-deepseek>=0.1.2
Requires-Dist: langchain-openai>=0.3.2
Requires-Dist: langgraph>=0.2.68
Requires-Dist: openai>=1.60.1
Requires-Dist: selenium>=4.29.0
Requires-Dist: sentence-transformers>=3.4.0
Requires-Dist: webdriver-manager>=4.0.2
